WITecSDK/__init__.py
WITecSDK/Modules/AFM.py
WITecSDK/Modules/ActiveSequencer.py
WITecSDK/Modules/ApertureFieldStop.py
WITecSDK/Modules/ApplicationControl.py
WITecSDK/Modules/AutoFocus.py
WITecSDK/Modules/BeamPath.py
WITecSDK/Modules/ConfigurationLoader.py
WITecSDK/Modules/DetectorOutput.py
WITecSDK/Modules/DistanceCurve.py
WITecSDK/Modules/EFMControl.py
WITecSDK/Modules/FastTimeSeries.py
WITecSDK/Modules/Heating.py
WITecSDK/Modules/HelperStructs.py
WITecSDK/Modules/Illumination.py
WITecSDK/Modules/ImageScan.py
WITecSDK/Modules/ImageScanMultipass.py
WITecSDK/Modules/LargeAreaScan.py
WITecSDK/Modules/LaserManager.py
WITecSDK/Modules/LaserPowerSeries.py
WITecSDK/Modules/LineScan.py
WITecSDK/Modules/ManualTopography.py
WITecSDK/Modules/ObjectiveTurret.py
WITecSDK/Modules/OwnCoordSystem.py
WITecSDK/Modules/ParameterNameGetter.py
WITecSDK/Modules/Polarization.py
WITecSDK/Modules/ProjectCreatorSaver.py
WITecSDK/Modules/SampleName.py
WITecSDK/Modules/ScanTable.py
WITecSDK/Modules/SilentSpectrum.py
WITecSDK/Modules/SingleSpectrum.py
WITecSDK/Modules/SlowTimeSeriesBase.py
WITecSDK/Modules/SlowTimeSeriesManual.py
WITecSDK/Modules/SlowTimeSeriesTimed.py
WITecSDK/Modules/SpectralAutofocus.py
WITecSDK/Modules/SpectralStitching.py
WITecSDK/Modules/Spectrograph.py
WITecSDK/Modules/StateManager.py
WITecSDK/Modules/TrueSurface.py
WITecSDK/Modules/VideoControl.py
WITecSDK/Modules/WITecControlVersionTester.py
WITecSDK/Modules/XYAxes.py
WITecSDK/Modules/ZAxis.py
WITecSDK/Modules/__init__.py
WITecSDK/Parameters/COMClient.py
WITecSDK/Parameters/COMEnumParameter.py
WITecSDK/Parameters/COMFillStatusParameter.py
WITecSDK/Parameters/COMFloatIntParameter.py
WITecSDK/Parameters/COMParameter.py
WITecSDK/Parameters/COMParameterBase.py
WITecSDK/Parameters/COMStatusParameter.py
WITecSDK/Parameters/COMSubSystemsList.py
WITecSDK/Parameters/__init__.py
witecsdk-1.5.4.dist-info/METADATA
witecsdk-1.5.4.dist-info/WHEEL
witecsdk-1.5.4.dist-info/top_level.txt
witecsdk-1.5.4.dist-info/RECORD
