Metadata-Version: 2.4
Name: WITecSDK
Version: 1.5.4
Summary: This package allows automation of WITec Control over COM
Author-email: Matthias Finger <info.witec@oxinst.com>
License: MIT License
Project-URL: Homepage, https://raman.oxinst.com/
Classifier: Programming Language :: Python :: 3
Classifier: License :: OSI Approved :: MIT License
Classifier: Operating System :: Microsoft :: Windows
Classifier: Intended Audience :: Developers
Requires-Python: >=3.10
Requires-Dist: comtypes>=1.2.0
